{"stats":{"minecraft:mined":{"minecraft:fire":1},"minecraft:killed":{"minecraft:spider":1,"minecraft:cow":1},"minecraft:used":{"minecraft:netherite_sword":4,"minecraft:cow_spawn_egg":1},"minecraft:custom":{"minecraft:jump":12,"minecraft:time_since_rest":1023,"minecraft:damage_dealt":180,"minecraft:sprint_one_cm":1248,"minecraft:damage_taken":200,"minecraft:play_time":1023,"minecraft:time_since_death":1023,"minecraft:walk_one_cm":1855,"minecraft:total_world_time":1067,"minecraft:mob_kills":2,"minecraft:fly_one_cm":2598}},"DataVersion":3700}